astrid.cpython-313-x86_64-linux-gnu.so
pippi/__init__.pxd
pippi/__init__.py
pippi/algos.py
pippi/benchmarks.py
pippi/chicago.ttf
pippi/chords.cpython-313-x86_64-linux-gnu.so
pippi/chords.pxd
pippi/defaults.c
pippi/defaults.cpython-313-x86_64-linux-gnu.so
pippi/defaults.pxd
pippi/defaults.pyx
pippi/dsp.c
pippi/dsp.cpython-313-x86_64-linux-gnu.so
pippi/dsp.pxd
pippi/dsp.pyx
pippi/events.c
pippi/events.cpython-313-x86_64-linux-gnu.so
pippi/events.pxd
pippi/events.pyx
pippi/fft.c
pippi/fft.cpython-313-x86_64-linux-gnu.so
pippi/fft.pxd
pippi/fft.pyx
pippi/frequtils.cpython-313-x86_64-linux-gnu.so
pippi/frequtils.pxd
pippi/fx.c
pippi/fx.cpython-313-x86_64-linux-gnu.so
pippi/fx.pxd
pippi/fx.pyx
pippi/graph.c
pippi/graph.cpython-313-x86_64-linux-gnu.so
pippi/graph.pxd
pippi/graph.pyx
pippi/interpolation.pxd
pippi/interpolation.pyx
pippi/intervals.cpython-313-x86_64-linux-gnu.so
pippi/lists.c
pippi/lists.cpython-313-x86_64-linux-gnu.so
pippi/lists.pxd
pippi/lists.pyx
pippi/microsound.c
pippi/microsound.cpython-313-x86_64-linux-gnu.so
pippi/microsound.pxd
pippi/microsound.pyx
pippi/midi.c
pippi/midi.cpython-313-x86_64-linux-gnu.so
pippi/midi.pxd
pippi/midi.pyx
pippi/mir.c
pippi/mir.cpython-313-x86_64-linux-gnu.so
pippi/mir.pxd
pippi/mir.pyx
pippi/noise.cpython-313-x86_64-linux-gnu.so
pippi/noise.pxd
pippi/oscs.c
pippi/oscs.cpython-313-x86_64-linux-gnu.so
pippi/oscs.pxd
pippi/oscs.pyx
pippi/rand.c
pippi/rand.cpython-313-x86_64-linux-gnu.so
pippi/rand.pxd
pippi/rand.pyx
pippi/scales.cpython-313-x86_64-linux-gnu.so
pippi/scales.pxd
pippi/shapes.c
pippi/shapes.cpython-313-x86_64-linux-gnu.so
pippi/shapes.pxd
pippi/shapes.pyx
pippi/soundbuffer.c
pippi/soundbuffer.cpython-313-x86_64-linux-gnu.so
pippi/soundbuffer.pxd
pippi/soundbuffer.pyx
pippi/soundfont.c
pippi/soundfont.cpython-313-x86_64-linux-gnu.so
pippi/soundfont.pxd
pippi/soundfont.pyx
pippi/tune.cpython-313-x86_64-linux-gnu.so
pippi/tune.pxd
pippi-2.0.0b14.dist-info/METADATA
pippi-2.0.0b14.dist-info/WHEEL
pippi-2.0.0b14.dist-info/top_level.txt
pippi-2.0.0b14.dist-info/RECORD
pippi-2.0.0b14.dist-info/licenses/LICENSE
