Metadata-Version: 2.4
Name: pippi
Version: 2.0.0b14
Summary: Computer music with Python
Author-email: He Can Jog <erik@hecanjog.com>
Project-URL: Homepage, https://git.sr.ht/~hecanjog/pippi
Project-URL: Documentation, https://pippi.world
Project-URL: Repository, https://git.sr.ht/~hecanjog/pippi
Project-URL: Changelog, https://git.sr.ht/~hecanjog/pippi/blob/main/CHANGELOG.md
Keywords: algorithmic,computer music
Classifier: Development Status :: 4 - Beta
Classifier: Intended Audience :: Developers
Classifier: Intended Audience :: Education
Classifier: Intended Audience :: Other Audience
Classifier: Natural Language :: English
Classifier: Operating System :: POSIX
Classifier: Operating System :: POSIX :: Linux
Classifier: Operating System :: Microsoft :: Windows
Classifier: Operating System :: MacOS
Classifier: Programming Language :: Cython
Classifier: Programming Language :: Python :: 3 :: Only
Classifier: Programming Language :: Python :: 3.8
Classifier: Programming Language :: Python :: 3.9
Classifier: Programming Language :: Python :: 3.10
Classifier: Programming Language :: Python :: 3.11
Classifier: Programming Language :: Python :: 3.12
Classifier: Programming Language :: Python :: 3.13
Classifier: Topic :: Artistic Software
Classifier: Topic :: Multimedia :: Sound/Audio
Classifier: Topic :: Multimedia :: Sound/Audio :: Sound Synthesis
Requires-Python: >=3.8
License-File: LICENSE
Requires-Dist: Cython
Requires-Dist: numpy
Requires-Dist: Pillow
Requires-Dist: soundfile
Requires-Dist: mido
Dynamic: license-file
